sagitta/__init__.py
sagitta/data_tools.py
sagitta/model_code.py
sagitta/sagitta.py
sagitta/model_state_dicts/age_model.pt
sagitta/model_state_dicts/av_model.pt
sagitta/model_state_dicts/pms_model.pt
Sagitta-1.2.2.dist-info/LICENSE
Sagitta-1.2.2.dist-info/METADATA
Sagitta-1.2.2.dist-info/WHEEL
Sagitta-1.2.2.dist-info/entry_points.txt
Sagitta-1.2.2.dist-info/top_level.txt
Sagitta-1.2.2.dist-info/RECORD
