Metadata-Version: 2.1
Name: Sagitta
Version: 1.2.2
Summary: A neural network based pipeline to identify pre-main sequence stars and estimate their ages.
Home-page: https://github.com/hutchresearch/Sagitta
Author: Aidan McBride, Ryan Lingg, Marina Kounkel, Kevin Covey, Brian Hutchinson
Author-email: marina.kounkel@vanderbilt.edu, mcbrida5@wwu.edu, linggr@wwu.edu
Classifier: Programming Language :: Python :: 3
Classifier: License :: OSI Approved :: MIT License
Classifier: Operating System :: OS Independent
Requires-Python: >=3.6
License-File: LICENSE
Requires-Dist: numpy
Requires-Dist: torch
Requires-Dist: astropy
Requires-Dist: astroquery
Requires-Dist: galpy
